entityscan/__init__.py
entityscan/__version__.py
entityscan/entity.py
entityscan/logging.py
entityscan/pipeline.py
entityscan/rules_db.py
entityscan/scanner.py
entityscan/engines/__init__.py
entityscan/engines/composites.py
entityscan/engines/literals.py
entityscan/engines/patterns.py
entityscan-22.4.25.dist-info/METADATA
entityscan-22.4.25.dist-info/WHEEL
entityscan-22.4.25.dist-info/top_level.txt
entityscan-22.4.25.dist-info/RECORD
