Metadata-Version: 2.1
Name: entityscan
Version: 22.4.25
Summary: Find entities using Hyperscan
Home-page: https://github.com/genomoncology/entityscan
Author: Ian Maurer
Author-email: ian@genomoncology.com
License: UNKNOWN
Platform: UNKNOWN
Classifier: License :: OSI Approved :: MIT License
Classifier: Development Status :: 4 - Beta
Classifier: Intended Audience :: Developers
Classifier: Natural Language :: English
Classifier: Operating System :: POSIX :: Linux
Classifier: Operating System :: MacOS :: MacOS X
Classifier: Operating System :: Microsoft :: Windows
Classifier: Programming Language :: Python :: 3
Classifier: Programming Language :: Python :: 3.6
Classifier: Programming Language :: Python :: 3.7
Classifier: Programming Language :: Python :: 3.8
Classifier: Programming Language :: Python :: 3.9
Classifier: Topic :: Scientific/Engineering
Requires-Python: >=3.6
Requires-Dist: hyperscan (==0.2.0)
Requires-Dist: pony (==0.7.16)
Requires-Dist: DAWG (==0.8.0)
